{"nodes": [{"id": "c_users_harsh_downloads_codebase_intelligence_project_backend_vector_db_chunker_py", "label": "chunker.py", "file_type": "code", "source_file": "backend/vector_db/chunker.py", "source_location": "L1"}, {"id": "vector_db_chunker_codechunker", "label": "CodeChunker", "file_type": "code", "source_file": "backend/vector_db/chunker.py", "source_location": "L14"}, {"id": "vector_db_chunker_codechunker_chunk_entity", "label": ".chunk_entity()", "file_type": "code", "source_file": "backend/vector_db/chunker.py", "source_location": "L22"}, {"id": "vector_db_chunker_rationale_1", "label": "AST-aware chunking: one chunk == one complete entity (function/class/method).  N", "file_type": "rationale", "source_file": "backend/vector_db/chunker.py", "source_location": "L1"}], "edges": [{"source": "c_users_harsh_downloads_codebase_intelligence_project_backend_vector_db_chunker_py", "target": "typing", "relation": "imports_from", "context": "import", "confidence": "EXTRACTED", "source_file": "backend/vector_db/chunker.py", "source_location": "L8", "weight": 1.0}, {"source": "c_users_harsh_downloads_codebase_intelligence_project_backend_vector_db_chunker_py", "target": "ast_parser", "relation": "imports_from", "context": "import", "confidence": "EXTRACTED", "source_file": "backend/vector_db/chunker.py", "source_location": "L11", "weight": 1.0}, {"source": "c_users_harsh_downloads_codebase_intelligence_project_backend_vector_db_chunker_py", "target": "vector_db_chunker_codechunker", "relation": "contains", "confidence": "EXTRACTED", "source_file": "backend/vector_db/chunker.py", "source_location": "L14", "weight": 1.0}, {"source": "vector_db_chunker_codechunker", "target": "vector_db_chunker_codechunker_chunk_entity", "relation": "method", "confidence": "EXTRACTED", "source_file": "backend/vector_db/chunker.py", "source_location": "L22", "weight": 1.0}, {"source": "vector_db_chunker_rationale_1", "target": "c_users_harsh_downloads_codebase_intelligence_project_backend_vector_db_chunker_py", "relation": "rationale_for", "confidence": "EXTRACTED", "source_file": "backend/vector_db/chunker.py", "source_location": "L1", "weight": 1.0}], "raw_calls": []}